{
 "object_id": "tex_0007783c95f3",
 "status": "ACCEPTED",
 "reason": "",
 "quality_status": "POSITIVE",
 "label_mode": "CANONICAL",
 "eligible": true,
 "artifact_valid": {
  "packed_layout": true,
  "rebaked_asset": false
 },
 "signal_dist": 0.1008,
 "gates": {
  "geometry_face_correspondence": true,
  "coverage>=99.9%": true,
  "finite_local_uv": true,
  "demand_nonneg_sum1": true,
  "chart_labels_finite": true,
  "beta_protocol_consistent": true
 },
 "quality_check": {
  "status": "OK",
  "R_uniform": 362,
  "R_teacher": 352,
  "bsignal_match": 0.9953,
  "G_global_eq": 0.152,
  "G_HF_eq": 0.1569,
  "overlap": 0
 },
 "hashes": {
  "geometry": "bec505aa40f852dd913e6633da5673d2298eb25ea9840dafa9ea86a025af8525",
  "chart": "999ae16cb1c5003452db6fb3091b9d26402af343da5b6aaa9b1bfa5ac399e758",
  "label": "ad1bd1e3b0b763d2c6ddda614512ed85355ddedb2de5123e51b17723d3de7625",
  "content_phash": "000bfbff60f2f076"
 },
 "n_charts": 48,
 "n_faces": 2204,
 "timings": {
  "parse_preflight": 3.63,
  "partuv_partfield": 8.35,
  "label_computation": 0.0,
  "packing_quality": 5.71,
  "serialization": 0.18,
  "total": 18.13,
  "download": 2.57,
  "preflight_fast": 0.0
 },
 "uid": "0007783c95f348d2ba0fc8d3be618afc",
 "preflight": {
  "ok": true,
  "reason": "",
  "n_faces": 2204,
  "n_verts": 1480,
  "n_geoms": 1,
  "tex_size": [
   512,
   512
  ],
  "tex_mode": "RGB"
 }
}